Workbook

Sheet Ventas mensuales
A1: Mes | B1: Linea_Producto | C1: Unidades_Vendidas | D1: Precio_Medio | E1: Ingresos_EUR | F1: Devoluciones | G1: Coste_Variable_EUR
A2: 2025-05 | B2: Café_en_grano | C2: 1240 | D2: 18.5 | E2: 22940 | F2: 12 | G2: 9176
A3: 2025-05 | B3: Cápsulas | C3: 3180 | D3: 9.9 | E3: 31482 | F3: 45 | G3: 15741
A4: 2025-05 | B4: Cold_Brew_botella | C4: 820 | D4: 5.5 | E4: 4510 | F4: 8 | G4: 2255
A5: 2025-05 | B5: Merchandising | C5: 310 | D5: 22 | E5: 6820 | F5: 2 | G5: 3410
A6: 2025-05 | B6: Suscripcion_mensual | C6: 425 | D6: 29 | E6: 12325 | F6: 3 | G6: 2465
A7: 2025-06 | B7: Café_en_grano | C7: 1310 | D7: 18.5 | E7: 24235 | F7: 15 | G7: 9694
A8: 2025-06 | B8: Cápsulas | C8: 3450 | D8: 9.9 | E8: 34155 | F8: 52 | G8: 17078
A9: 2025-06 | B9: Cold_Brew_botella | C9: 1180 | D9: 5.5 | E9: 6490 | F9: 11 | G9: 3245
A10: 2025-06 | B10: Merchandising | C10: 290 | D10: 22 | E10: 6380 | F10: 3 | G10: 3190
A11: 2025-06 | B11: Suscripcion_mensual | C11: 468 | D11: 29 | E11: 13572 | F11: 4 | G11: 2714
A12: 2025-07 | B12: Café_en_grano | C12: 1180 | D12: 18.5 | E12: 21830 | F12: 18 | G12: 8732
A13: 2025-07 | B13: Cápsulas | C13: 3320 | D13: 9.9 | E13: 32868 | F13: 40 | G13: 16434
... A61: 2026-04 | B61: Suscripcion_mensual | C61: 841 | D61: 29 | E61: 24389 | F61: 5 | G61: 4878

Sheet Resumen mensual
A1: Mes | B1: Ingresos totales | C1: Unidades totales | D1: Coste variable total | E1: Margen bruto | F1: Margen %
A2: 2025-05 | B2: =SUMIFS('Ventas mensuales'!$E$2:$E$61,'Ventas mensuales'!$A$2:$A$61,A2) | C2: =SUMIFS('Ventas mensuales'!$C$2:$C$61,'Ventas mensuales'!$A$2:$A$61,A2) | D2: =SUMIFS('Ventas mensuales'!$G$2:$G$61,'Ventas mensuales'!$A$2:$A$61,A2) | E2: =B2-D2 | F2: =IF(B2=0,0,E2/B2)
A3: 2025-06 | B3: =SUMIFS('Ventas mensuales'!$E$2:$E$61,'Ventas mensuales'!$A$2:$A$61,A3) | C3: =SUMIFS('Ventas mensuales'!$C$2:$C$61,'Ventas mensuales'!$A$2:$A$61,A3) | D3: =SUMIFS('Ventas mensuales'!$G$2:$G$61,'Ventas mensuales'!$A$2:$A$61,A3) | E3: =B3-D3 | F3: =IF(B3=0,0,E3/B3)
A4: 2025-07 | B4: =SUMIFS('Ventas mensuales'!$E$2:$E$61,'Ventas mensuales'!$A$2:$A$61,A4) | C4: =SUMIFS('Ventas mensuales'!$C$2:$C$61,'Ventas mensuales'!$A$2:$A$61,A4) | D4: =SUMIFS('Ventas mensuales'!$G$2:$G$61,'Ventas mensuales'!$A$2:$A$61,A4) | E4: =B4-D4 | F4: =IF(B4=0,0,E4/B4)
A5: 2025-08 | B5: =SUMIFS('Ventas mensuales'!$E$2:$E$61,'Ventas mensuales'!$A$2:$A$61,A5) | C5: =SUMIFS('Ventas mensuales'!$C$2:$C$61,'Ventas mensuales'!$A$2:$A$61,A5) | D5: =SUMIFS('Ventas mensuales'!$G$2:$G$61,'Ventas mensuales'!$A$2:$A$61,A5) | E5: =B5-D5 | F5: =IF(B5=0,0,E5/B5)
A6: 2025-09 | B6: =SUMIFS('Ventas mensuales'!$E$2:$E$61,'Ventas mensuales'!$A$2:$A$61,A6) | C6: =SUMIFS('Ventas mensuales'!$C$2:$C$61,'Ventas mensuales'!$A$2:$A$61,A6) | D6: =SUMIFS('Ventas mensuales'!$G$2:$G$61,'Ventas mensuales'!$A$2:$A$61,A6) | E6: =B6-D6 | F6: =IF(B6=0,0,E6/B6)
A7: 2025-10 | B7: =SUMIFS('Ventas mensuales'!$E$2:$E$61,'Ventas mensuales'!$A$2:$A$61,A7) | C7: =SUMIFS('Ventas mensuales'!$C$2:$C$61,'Ventas mensuales'!$A$2:$A$61,A7) | D7: =SUMIFS('Ventas mensuales'!$G$2:$G$61,'Ventas mensuales'!$A$2:$A$61,A7) | E7: =B7-D7 | F7: =IF(B7=0,0,E7/B7)
A8: 2025-11 | B8: =SUMIFS('Ventas mensuales'!$E$2:$E$61,'Ventas mensuales'!$A$2:$A$61,A8) | C8: =SUMIFS('Ventas mensuales'!$C$2:$C$61,'Ventas mensuales'!$A$2:$A$61,A8) | D8: =SUMIFS('Ventas mensuales'!$G$2:$G$61,'Ventas mensuales'!$A$2:$A$61,A8) | E8: =B8-D8 | F8: =IF(B8=0,0,E8/B8)
A9: 2025-12 | B9: =SUMIFS('Ventas mensuales'!$E$2:$E$61,'Ventas mensuales'!$A$2:$A$61,A9) | C9: =SUMIFS('Ventas mensuales'!$C$2:$C$61,'Ventas mensuales'!$A$2:$A$61,A9) | D9: =SUMIFS('Ventas mensuales'!$G$2:$G$61,'Ventas mensuales'!$A$2:$A$61,A9) | E9: =B9-D9 | F9: =IF(B9=0,0,E9/B9)
A10: 2026-01 | B10: =SUMIFS('Ventas mensuales'!$E$2:$E$61,'Ventas mensuales'!$A$2:$A$61,A10) | C10: =SUMIFS('Ventas mensuales'!$C$2:$C$61,'Ventas mensuales'!$A$2:$A$61,A10) | D10: =SUMIFS('Ventas mensuales'!$G$2:$G$61,'Ventas mensuales'!$A$2:$A$61,A10) | E10: =B10-D10 | F10: =IF(B10=0,0,E10/B10)
A11: 2026-02 | B11: =SUMIFS('Ventas mensuales'!$E$2:$E$61,'Ventas mensuales'!$A$2:$A$61,A11) | C11: =SUMIFS('Ventas mensuales'!$C$2:$C$61,'Ventas mensuales'!$A$2:$A$61,A11) | D11: =SUMIFS('Ventas mensuales'!$G$2:$G$61,'Ventas mensuales'!$A$2:$A$61,A11) | E11: =B11-D11 | F11: =IF(B11=0,0,E11/B11)
A12: 2026-03 | B12: =SUMIFS('Ventas mensuales'!$E$2:$E$61,'Ventas mensuales'!$A$2:$A$61,A12) | C12: =SUMIFS('Ventas mensuales'!$C$2:$C$61,'Ventas mensuales'!$A$2:$A$61,A12) | D12: =SUMIFS('Ventas mensuales'!$G$2:$G$61,'Ventas mensuales'!$A$2:$A$61,A12) | E12: =B12-D12 | F12: =IF(B12=0,0,E12/B12)
A13: 2026-04 | B13: =SUMIFS('Ventas mensuales'!$E$2:$E$61,'Ventas mensuales'!$A$2:$A$61,A13) | C13: =SUMIFS('Ventas mensuales'!$C$2:$C$61,'Ventas mensuales'!$A$2:$A$61,A13) | D13: =SUMIFS('Ventas mensuales'!$G$2:$G$61,'Ventas mensuales'!$A$2:$A$61,A13) | E13: =B13-D13 | F13: =IF(B13=0,0,E13/B13)
